cmlibs/__init__.py
cmlibs/exporter/__init__.py
cmlibs/exporter/base.py
cmlibs/exporter/baseimage.py
cmlibs/exporter/errors.py
cmlibs/exporter/flatmapsvg.py
cmlibs/exporter/image.py
cmlibs/exporter/mbfxml.py
cmlibs/exporter/stl.py
cmlibs/exporter/thumbnail.py
cmlibs/exporter/vtk.py
cmlibs/exporter/wavefront.py
cmlibs/exporter/webgl.py
cmlibs/exporter/utils/__init__.py
cmlibs/exporter/utils/beziercurve.py
cmlibs/exporter/utils/continuity.py
cmlibs_exporter-0.10.1.dist-info/licenses/LICENSE
cmlibs_exporter-0.10.1.dist-info/METADATA
cmlibs_exporter-0.10.1.dist-info/WHEEL
cmlibs_exporter-0.10.1.dist-info/top_level.txt
cmlibs_exporter-0.10.1.dist-info/RECORD
