Metadata-Version: 2.4
Name: cmlibs.exporter
Version: 0.10.1
Summary: Export CMLibs Zinc data to common mesh formats.
Author-email: Hugh Sorby <h.sorby@auckland.ac.nz>
License-Expression: Apache-2.0
Project-URL: Homepage, https://cmlibs.org
Project-URL: Repository, https://github.com/CMLibs-Python/cmlibs.exporter
Keywords: Export,CMLibs,Zinc
Classifier: Programming Language :: Python :: 3
Classifier: Operating System :: OS Independent
Classifier: Topic :: Scientific/Engineering :: Medical Science Apps.
Requires-Python: >=3.8
License-File: LICENSE
Requires-Dist: cmlibs.argon>=0.4.0
Requires-Dist: cmlibs.zinc
Requires-Dist: exf2mbfxml
Requires-Dist: packaging
Requires-Dist: svgpathtools_light
Provides-Extra: opengl-hardware
Requires-Dist: PySide6; extra == "opengl-hardware"
Provides-Extra: opengl-software
Requires-Dist: PyOpenGL; extra == "opengl-software"
Dynamic: license-file
